LICENSE
MANIFEST.in
README.rst
requirements.txt
setup.cfg
setup.py
versioneer.py
datashape/__init__.py
datashape/_version.py
datashape/coretypes.py
datashape/discovery.py
datashape/dispatch.py
datashape/error.py
datashape/internal_utils.py
datashape/lexer.py
datashape/parser.py
datashape/predicates.py
datashape/promote.py
datashape/py2help.py
datashape/type_symbol_table.py
datashape/typesets.py
datashape/user.py
datashape/util.py
datashape/validation.py
datashape.egg-info/PKG-INFO
datashape.egg-info/SOURCES.txt
datashape.egg-info/dependency_links.txt
datashape.egg-info/not-zip-safe
datashape.egg-info/pbr.json
datashape.egg-info/requires.txt
datashape.egg-info/top_level.txt
datashape/tests/__init__.py
datashape/tests/test_coretypes.py
datashape/tests/test_creation.py
datashape/tests/test_discovery.py
datashape/tests/test_lexer.py
datashape/tests/test_operations.py
datashape/tests/test_parser.py
datashape/tests/test_predicates.py
datashape/tests/test_promote.py
datashape/tests/test_str.py
datashape/tests/test_typeset.py
datashape/tests/test_user.py
datashape/tests/test_util.py
datashape/tests/test_version.py
docs/source/grammar.rst
docs/source/index.rst
docs/source/overview.rst
docs/source/pattern_matching.rst
docs/source/releases.rst
docs/source/types.rst