Metadata-Version: 1.1
Name: datashape
Version: 0.4.7
Summary: A data description language.
Home-page: http://datashape.readthedocs.org/en/latest/
Author: Continuum Analytics
Author-email: blaze-dev@continuum.io
License: BSD
Keywords: data language
Platform: UNKNOWN
Classifier: Development Status :: 3 - Alpha
Classifier: Intended Audience :: Developers
Classifier: Topic :: Software Development
Classifier: License :: OSI Approved :: BSD License
